openfhe/__init__.py
openfhe/build-config.txt
openfhe/openfhe.cpython-310-x86_64-linux-gnu.so
openfhe/openfhe.cpython-311-x86_64-linux-gnu.so
openfhe/openfhe.cpython-312-x86_64-linux-gnu.so
openfhe/openfhe.cpython-37m-x86_64-linux-gnu.so
openfhe/openfhe.cpython-38-x86_64-linux-gnu.so
openfhe/openfhe.cpython-39-x86_64-linux-gnu.so
openfhe/lib/libOPENFHEbinfhe.so.1
openfhe/lib/libOPENFHEcore.so.1
openfhe/lib/libOPENFHEpke.so.1
openfhe/lib/libgomp.so
gpufhe_wrapper-0.0.6.dist-info/LICENSE
gpufhe_wrapper-0.0.6.dist-info/METADATA
gpufhe_wrapper-0.0.6.dist-info/WHEEL
gpufhe_wrapper-0.0.6.dist-info/top_level.txt
gpufhe_wrapper-0.0.6.dist-info/RECORD
