Metadata-Version: 2.1
Name: gpufhe-wrapper
Version: 0.0.6
Summary: A Python wrapper for OpenFHE to generate context for pyFHE
Home-page: https://github.com/openfheorg/openfhe-python
Author: Zhuoran Ji
Author-email: jizhuoran.work@gmail.com
License: BSD-2-Clause
Classifier: Operating System :: POSIX :: Linux
Requires-Python: >=3.7
License-File: LICENSE
